tcc_otel/__init__.py
tcc_otel/_base.py
tcc_otel/config.py
tcc_otel/langchain.py
tcc_otel-0.1.0.dist-info/METADATA
tcc_otel-0.1.0.dist-info/WHEEL
tcc_otel-0.1.0.dist-info/licenses/LICENSE
tcc_otel-0.1.0.dist-info/RECORD
