Metadata-Version: 2.4
Name: tcc-otel
Version: 0.1.0
Summary: The Context Company OpenTelemetry SDK for Python
Project-URL: Homepage, https://thecontext.company
Project-URL: Documentation, https://docs.thecontext.company
Project-URL: Repository, https://github.com/contextcompany/tcc
Project-URL: Issues, https://github.com/contextcompany/tcc/issues
Author-email: The Context Company <support@thecontext.company>
License: MIT
License-File: LICENSE
Keywords: langchain,llm,observability,opentelemetry,tracing
Classifier: Development Status :: 4 - Beta
Classifier: Intended Audience :: Developers
Classifier: License :: OSI Approved :: MIT License
Classifier: Programming Language :: Python :: 3
Classifier: Programming Language :: Python :: 3.9
Classifier: Programming Language :: Python :: 3.10
Classifier: Programming Language :: Python :: 3.11
Classifier: Programming Language :: Python :: 3.12
Classifier: Programming Language :: Python :: 3.13
Classifier: Topic :: Software Development :: Libraries :: Python Modules
Classifier: Topic :: System :: Monitoring
Requires-Python: >=3.9
Requires-Dist: opentelemetry-api>=1.29.0
Requires-Dist: opentelemetry-exporter-otlp>=1.29.0
Requires-Dist: opentelemetry-sdk>=1.29.0
Provides-Extra: dev
Requires-Dist: pytest-asyncio>=0.21.0; extra == 'dev'
Requires-Dist: pytest>=7.0.0; extra == 'dev'
Requires-Dist: python-dotenv>=1.0.0; extra == 'dev'
Provides-Extra: langchain
Requires-Dist: opentelemetry-instrumentation-langchain>=0.47.3; extra == 'langchain'
